[
    {
        "colo": "Default",
        "ip": "2606:4700:132:fa9d:6f5:42e0:2bf7:23b1",
        "latency": 1,
        "line": "CM",
        "loss": 0,
        "node": "WW_HK",
        "speed": 309,
        "time": "2024-11-04 14:16:26"
    },
    {
        "colo": "Default",
        "ip": "2606:4700:132:64f9:7ac3:24d1:cc28:a573",
        "latency": 1,
        "line": "CM",
        "loss": 0,
        "node": "WW_HK",
        "speed": 308,
        "time": "2024-11-04 14:16:26"
    },
    {
        "colo": "Default",
        "ip": "2606:4700:132:22cb:cb84:c55e:dcfc:600c",
        "latency": 1,
        "line": "CM",
        "loss": 0,
        "node": "WW_HK",
        "speed": 308,
        "time": "2024-11-04 14:16:26"
    },
    {
        "colo": "Default",
        "ip": "2606:4700:132:5d57:2c3e:a30f:4fb:69ef",
        "latency": 7,
        "line": "CM",
        "loss": 0,
        "node": "WW_HK",
        "speed": 308,
        "time": "2024-11-04 14:16:26"
    },
    {
        "colo": "Default",
        "ip": "2606:4700:132:705:9c5:4c05:584:a2b4",
        "latency": 20,
        "line": "CM",
        "loss": 0,
        "node": "WW_HK",
        "speed": 307,
        "time": "2024-11-04 14:16:26"
    },
    {
        "colo": "Default",
        "ip": "2606:4700:4404:c12c:89fc:bf62:e012:1d28",
        "latency": 1,
        "line": "CT",
        "loss": 0,
        "node": "WEBH",
        "speed": 308,
        "time": "2024-11-04 14:15:25"
    },
    {
        "colo": "Default",
        "ip": "2606:4700:4404:1f39:7cc:9f43:abb4:2ae8",
        "latency": 1,
        "line": "CT",
        "loss": 0,
        "node": "WEBH",
        "speed": 307,
        "time": "2024-11-04 14:15:27"
    },
    {
        "colo": "Default",
        "ip": "2606:4700:9b0b:6b33:35f:4d8:70aa:fc27",
        "latency": 24,
        "line": "CT",
        "loss": 0,
        "node": "WEBH",
        "speed": 307,
        "time": "2024-11-04 14:15:27"
    },
    {
        "colo": "Default",
        "ip": "2606:4700:9b0b:d7aa:1ff3:e334:9a0e:ddaf",
        "latency": 20,
        "line": "CT",
        "loss": 0,
        "node": "WEBH",
        "speed": 307,
        "time": "2024-11-04 14:15:26"
    },
    {
        "colo": "Default",
        "ip": "2606:4700:9b0b:831f:278:9afa:a5fd:f364",
        "latency": 24,
        "line": "CT",
        "loss": 0,
        "node": "WEBH",
        "speed": 307,
        "time": "2024-11-04 14:15:24"
    },
    {
        "colo": "Default",
        "ip": "2606:4700:132:fa9d:6f5:42e0:2bf7:23b1",
        "latency": 1,
        "line": "CU",
        "loss": 0,
        "node": "WW_HK",
        "speed": 309,
        "time": "2024-11-04 14:16:26"
    },
    {
        "colo": "Default",
        "ip": "2606:4700:132:64f9:7ac3:24d1:cc28:a573",
        "latency": 1,
        "line": "CU",
        "loss": 0,
        "node": "WW_HK",
        "speed": 308,
        "time": "2024-11-04 14:16:26"
    },
    {
        "colo": "Default",
        "ip": "2606:4700:132:22cb:cb84:c55e:dcfc:600c",
        "latency": 1,
        "line": "CU",
        "loss": 0,
        "node": "WW_HK",
        "speed": 308,
        "time": "2024-11-04 14:16:26"
    },
    {
        "colo": "Default",
        "ip": "2606:4700:132:5d57:2c3e:a30f:4fb:69ef",
        "latency": 7,
        "line": "CU",
        "loss": 0,
        "node": "WW_HK",
        "speed": 308,
        "time": "2024-11-04 14:16:26"
    },
    {
        "colo": "Default",
        "ip": "2606:4700:132:705:9c5:4c05:584:a2b4",
        "latency": 20,
        "line": "CU",
        "loss": 0,
        "node": "WW_HK",
        "speed": 307,
        "time": "2024-11-04 14:16:26"
    }
]