[
    {
        "colo": "Default",
        "ip": "2606:4700:90cf:7b6:61c6:e7b4:a138:17a4",
        "latency": 60,
        "line": "CM",
        "loss": 0,
        "node": "WEBH",
        "speed": 309,
        "time": "2024-12-16 01:24:56"
    },
    {
        "colo": "Default",
        "ip": "2606:4700:90cf:4ed7:66d:65e2:adaf:82fe",
        "latency": 80,
        "line": "CM",
        "loss": 0,
        "node": "WEBH",
        "speed": 308,
        "time": "2024-12-16 01:24:56"
    },
    {
        "colo": "Default",
        "ip": "2606:4700:90cf:baa8:53cc:605e:8655:a5fc",
        "latency": 87,
        "line": "CM",
        "loss": 0,
        "node": "WEBH",
        "speed": 308,
        "time": "2024-12-16 01:24:56"
    },
    {
        "colo": "Default",
        "ip": "2606:4700:90cf:d2cf:4c48:21dc:ad0f:5c13",
        "latency": 52,
        "line": "CM",
        "loss": 0,
        "node": "WEBH",
        "speed": 307,
        "time": "2024-12-16 01:24:56"
    },
    {
        "colo": "Default",
        "ip": "2606:4700:9b04:b126:c8d3:274c:63f7:c3c5",
        "latency": 21,
        "line": "CM",
        "loss": 0,
        "node": "WEBH",
        "speed": 307,
        "time": "2024-12-16 01:14:56"
    },
    {
        "colo": "Default",
        "ip": "2606:4700:90cf:7b6:61c6:e7b4:a138:17a4",
        "latency": 60,
        "line": "CT",
        "loss": 0,
        "node": "WEBH",
        "speed": 309,
        "time": "2024-12-16 01:24:56"
    },
    {
        "colo": "Default",
        "ip": "2606:4700:90cf:4ed7:66d:65e2:adaf:82fe",
        "latency": 80,
        "line": "CT",
        "loss": 0,
        "node": "WEBH",
        "speed": 308,
        "time": "2024-12-16 01:24:56"
    },
    {
        "colo": "Default",
        "ip": "2606:4700:90cf:baa8:53cc:605e:8655:a5fc",
        "latency": 87,
        "line": "CT",
        "loss": 0,
        "node": "WEBH",
        "speed": 308,
        "time": "2024-12-16 01:24:56"
    },
    {
        "colo": "Default",
        "ip": "2606:4700:90cf:d2cf:4c48:21dc:ad0f:5c13",
        "latency": 52,
        "line": "CT",
        "loss": 0,
        "node": "WEBH",
        "speed": 307,
        "time": "2024-12-16 01:24:56"
    },
    {
        "colo": "Default",
        "ip": "2606:4700:9b04:b126:c8d3:274c:63f7:c3c5",
        "latency": 21,
        "line": "CT",
        "loss": 0,
        "node": "WEBH",
        "speed": 307,
        "time": "2024-12-16 01:14:56"
    },
    {
        "colo": "Default",
        "ip": "2606:4700:90cf:7b6:61c6:e7b4:a138:17a4",
        "latency": 60,
        "line": "CU",
        "loss": 0,
        "node": "WEBH",
        "speed": 309,
        "time": "2024-12-16 01:24:56"
    },
    {
        "colo": "Default",
        "ip": "2606:4700:90cf:4ed7:66d:65e2:adaf:82fe",
        "latency": 80,
        "line": "CU",
        "loss": 0,
        "node": "WEBH",
        "speed": 308,
        "time": "2024-12-16 01:24:56"
    },
    {
        "colo": "Default",
        "ip": "2606:4700:90cf:baa8:53cc:605e:8655:a5fc",
        "latency": 87,
        "line": "CU",
        "loss": 0,
        "node": "WEBH",
        "speed": 308,
        "time": "2024-12-16 01:24:56"
    },
    {
        "colo": "Default",
        "ip": "2606:4700:90cf:d2cf:4c48:21dc:ad0f:5c13",
        "latency": 52,
        "line": "CU",
        "loss": 0,
        "node": "WEBH",
        "speed": 307,
        "time": "2024-12-16 01:24:56"
    },
    {
        "colo": "Default",
        "ip": "2606:4700:9b04:b126:c8d3:274c:63f7:c3c5",
        "latency": 21,
        "line": "CU",
        "loss": 0,
        "node": "WEBH",
        "speed": 307,
        "time": "2024-12-16 01:14:56"
    }
]