[
    {
        "colo": "Default",
        "ip": "2606:4700:9a9e:1400:f1f1:fa79:af07:bb3a",
        "latency": 158,
        "line": "CM",
        "loss": 0,
        "node": "CBUS",
        "speed": 573,
        "time": "2024-09-29 05:19:40"
    },
    {
        "colo": "Default",
        "ip": "2606:4700:8d7a:3252:b42c:52f5:f591:94a3",
        "latency": 159,
        "line": "CM",
        "loss": 0,
        "node": "CBUS",
        "speed": 507,
        "time": "2024-09-29 05:19:41"
    },
    {
        "colo": "Default",
        "ip": "2606:4700:9a9e:1a78:72f2:e845:ba9:7c1a",
        "latency": 158,
        "line": "CM",
        "loss": 0,
        "node": "CBUS",
        "speed": 450,
        "time": "2024-09-29 05:19:41"
    },
    {
        "colo": "Default",
        "ip": "2606:4700:8d7a:1ece:c5a6:5a8f:3dcb:80d2",
        "latency": 157,
        "line": "CM",
        "loss": 0,
        "node": "CBUS",
        "speed": 423,
        "time": "2024-09-29 05:19:40"
    },
    {
        "colo": "Default",
        "ip": "2606:4700:8d7a:78b9:a512:1ed3:9f82:2b56",
        "latency": 159,
        "line": "CM",
        "loss": 0,
        "node": "CBUS",
        "speed": 407,
        "time": "2024-09-29 05:19:40"
    },
    {
        "colo": "Default",
        "ip": "2606:4700:8d94:d66d:f679:b811:8a01:8ce8",
        "latency": 19,
        "line": "CT",
        "loss": 0,
        "node": "WEBH",
        "speed": 308,
        "time": "2024-09-29 05:25:47"
    },
    {
        "colo": "Default",
        "ip": "2606:4700:8d94:953:f6f1:4aba:4309:e6ce",
        "latency": 20,
        "line": "CT",
        "loss": 0,
        "node": "WEBH",
        "speed": 308,
        "time": "2024-09-29 05:25:47"
    },
    {
        "colo": "Default",
        "ip": "2606:4700:8d94:bf6c:4859:862d:e013:36d1",
        "latency": 20,
        "line": "CT",
        "loss": 0,
        "node": "WEBH",
        "speed": 307,
        "time": "2024-09-29 05:25:47"
    },
    {
        "colo": "Default",
        "ip": "2606:4700:8d94:c6e9:eb18:76a0:f648:5d49",
        "latency": 23,
        "line": "CT",
        "loss": 0,
        "node": "WEBH",
        "speed": 307,
        "time": "2024-09-29 05:25:47"
    },
    {
        "colo": "Default",
        "ip": "2606:4700:8d94:ce90:559c:543b:8877:5fe1",
        "latency": 24,
        "line": "CT",
        "loss": 0,
        "node": "WEBH",
        "speed": 307,
        "time": "2024-09-29 05:25:47"
    },
    {
        "colo": "Default",
        "ip": "2606:4700:9a9e:1400:f1f1:fa79:af07:bb3a",
        "latency": 158,
        "line": "CU",
        "loss": 0,
        "node": "CBUS",
        "speed": 573,
        "time": "2024-09-29 05:19:40"
    },
    {
        "colo": "Default",
        "ip": "2606:4700:8d7a:3252:b42c:52f5:f591:94a3",
        "latency": 159,
        "line": "CU",
        "loss": 0,
        "node": "CBUS",
        "speed": 507,
        "time": "2024-09-29 05:19:41"
    },
    {
        "colo": "Default",
        "ip": "2606:4700:9a9e:1a78:72f2:e845:ba9:7c1a",
        "latency": 158,
        "line": "CU",
        "loss": 0,
        "node": "CBUS",
        "speed": 450,
        "time": "2024-09-29 05:19:41"
    },
    {
        "colo": "Default",
        "ip": "2606:4700:8d7a:1ece:c5a6:5a8f:3dcb:80d2",
        "latency": 157,
        "line": "CU",
        "loss": 0,
        "node": "CBUS",
        "speed": 423,
        "time": "2024-09-29 05:19:40"
    },
    {
        "colo": "Default",
        "ip": "2606:4700:8d7a:78b9:a512:1ed3:9f82:2b56",
        "latency": 159,
        "line": "CU",
        "loss": 0,
        "node": "CBUS",
        "speed": 407,
        "time": "2024-09-29 05:19:40"
    }
]