[
    {
        "colo": "Default",
        "ip": "2606:4700:9a97:c670:77d7:49df:8365:a4bb",
        "latency": 19,
        "line": "CM",
        "loss": 0,
        "node": "WEBH",
        "speed": 309,
        "time": "2025-02-04 18:24:22"
    },
    {
        "colo": "Default",
        "ip": "2606:4700:9a97:8037:6a5f:3989:86e1:8040",
        "latency": 20,
        "line": "CM",
        "loss": 0,
        "node": "WEBH",
        "speed": 309,
        "time": "2025-02-04 18:24:21"
    },
    {
        "colo": "Default",
        "ip": "2606:4700:9a97:5e25:ec93:a75d:ac55:a284",
        "latency": 22,
        "line": "CM",
        "loss": 0,
        "node": "WEBH",
        "speed": 308,
        "time": "2025-02-04 18:24:22"
    },
    {
        "colo": "Default",
        "ip": "2606:4700:9a97:7cf6:e8c2:6555:3928:53",
        "latency": 19,
        "line": "CM",
        "loss": 0,
        "node": "WEBH",
        "speed": 308,
        "time": "2025-02-04 18:24:21"
    },
    {
        "colo": "Default",
        "ip": "2606:4700:9a97:e25d:78a:929f:e500:4ec",
        "latency": 19,
        "line": "CM",
        "loss": 0,
        "node": "WEBH",
        "speed": 307,
        "time": "2025-02-04 18:24:22"
    },
    {
        "colo": "Default",
        "ip": "2606:4700:9a97:c670:77d7:49df:8365:a4bb",
        "latency": 19,
        "line": "CT",
        "loss": 0,
        "node": "WEBH",
        "speed": 309,
        "time": "2025-02-04 18:24:22"
    },
    {
        "colo": "Default",
        "ip": "2606:4700:9a97:8037:6a5f:3989:86e1:8040",
        "latency": 20,
        "line": "CT",
        "loss": 0,
        "node": "WEBH",
        "speed": 309,
        "time": "2025-02-04 18:24:21"
    },
    {
        "colo": "Default",
        "ip": "2606:4700:9a97:5e25:ec93:a75d:ac55:a284",
        "latency": 22,
        "line": "CT",
        "loss": 0,
        "node": "WEBH",
        "speed": 308,
        "time": "2025-02-04 18:24:22"
    },
    {
        "colo": "Default",
        "ip": "2606:4700:9a97:7cf6:e8c2:6555:3928:53",
        "latency": 19,
        "line": "CT",
        "loss": 0,
        "node": "WEBH",
        "speed": 308,
        "time": "2025-02-04 18:24:21"
    },
    {
        "colo": "Default",
        "ip": "2606:4700:9a97:e25d:78a:929f:e500:4ec",
        "latency": 19,
        "line": "CT",
        "loss": 0,
        "node": "WEBH",
        "speed": 307,
        "time": "2025-02-04 18:24:22"
    },
    {
        "colo": "Default",
        "ip": "2606:4700:9a97:c670:77d7:49df:8365:a4bb",
        "latency": 19,
        "line": "CU",
        "loss": 0,
        "node": "WEBH",
        "speed": 309,
        "time": "2025-02-04 18:24:22"
    },
    {
        "colo": "Default",
        "ip": "2606:4700:9a97:8037:6a5f:3989:86e1:8040",
        "latency": 20,
        "line": "CU",
        "loss": 0,
        "node": "WEBH",
        "speed": 309,
        "time": "2025-02-04 18:24:21"
    },
    {
        "colo": "Default",
        "ip": "2606:4700:9a97:5e25:ec93:a75d:ac55:a284",
        "latency": 22,
        "line": "CU",
        "loss": 0,
        "node": "WEBH",
        "speed": 308,
        "time": "2025-02-04 18:24:22"
    },
    {
        "colo": "Default",
        "ip": "2606:4700:9a97:7cf6:e8c2:6555:3928:53",
        "latency": 19,
        "line": "CU",
        "loss": 0,
        "node": "WEBH",
        "speed": 308,
        "time": "2025-02-04 18:24:21"
    },
    {
        "colo": "Default",
        "ip": "2606:4700:9a97:e25d:78a:929f:e500:4ec",
        "latency": 19,
        "line": "CU",
        "loss": 0,
        "node": "WEBH",
        "speed": 307,
        "time": "2025-02-04 18:24:22"
    }
]