[
    {
        "colo": "Default",
        "ip": "2606:4700:83bd:add7:80b2:e542:83da:d562",
        "latency": 22,
        "line": "CM",
        "loss": 0,
        "node": "WEBH",
        "speed": 311,
        "time": "2025-01-05 20:54:43"
    },
    {
        "colo": "Default",
        "ip": "2606:4700:8d9f:42de:c9e6:952f:3f8b:ed58",
        "latency": 20,
        "line": "CM",
        "loss": 0,
        "node": "WEBH",
        "speed": 308,
        "time": "2025-01-05 20:54:45"
    },
    {
        "colo": "Default",
        "ip": "2606:4700:83bd:1803:652a:c1ed:5511:68cf",
        "latency": 20,
        "line": "CM",
        "loss": 0,
        "node": "WEBH",
        "speed": 308,
        "time": "2025-01-05 20:54:44"
    },
    {
        "colo": "Default",
        "ip": "2606:4700:8d9f:f35d:a917:935:439:e52c",
        "latency": 20,
        "line": "CM",
        "loss": 0,
        "node": "WEBH",
        "speed": 308,
        "time": "2025-01-05 20:54:46"
    },
    {
        "colo": "Default",
        "ip": "2606:4700:8d9f:db46:4567:4600:a0c4:d3d3",
        "latency": 20,
        "line": "CM",
        "loss": 0,
        "node": "WEBH",
        "speed": 307,
        "time": "2025-01-05 20:54:43"
    },
    {
        "colo": "Default",
        "ip": "2606:4700:83bd:add7:80b2:e542:83da:d562",
        "latency": 22,
        "line": "CT",
        "loss": 0,
        "node": "WEBH",
        "speed": 311,
        "time": "2025-01-05 20:54:43"
    },
    {
        "colo": "Default",
        "ip": "2606:4700:8d9f:42de:c9e6:952f:3f8b:ed58",
        "latency": 20,
        "line": "CT",
        "loss": 0,
        "node": "WEBH",
        "speed": 308,
        "time": "2025-01-05 20:54:45"
    },
    {
        "colo": "Default",
        "ip": "2606:4700:83bd:1803:652a:c1ed:5511:68cf",
        "latency": 20,
        "line": "CT",
        "loss": 0,
        "node": "WEBH",
        "speed": 308,
        "time": "2025-01-05 20:54:44"
    },
    {
        "colo": "Default",
        "ip": "2606:4700:8d9f:f35d:a917:935:439:e52c",
        "latency": 20,
        "line": "CT",
        "loss": 0,
        "node": "WEBH",
        "speed": 308,
        "time": "2025-01-05 20:54:46"
    },
    {
        "colo": "Default",
        "ip": "2606:4700:8d9f:db46:4567:4600:a0c4:d3d3",
        "latency": 20,
        "line": "CT",
        "loss": 0,
        "node": "WEBH",
        "speed": 307,
        "time": "2025-01-05 20:54:43"
    },
    {
        "colo": "Default",
        "ip": "2606:4700:83bd:add7:80b2:e542:83da:d562",
        "latency": 22,
        "line": "CU",
        "loss": 0,
        "node": "WEBH",
        "speed": 311,
        "time": "2025-01-05 20:54:43"
    },
    {
        "colo": "Default",
        "ip": "2606:4700:8d9f:42de:c9e6:952f:3f8b:ed58",
        "latency": 20,
        "line": "CU",
        "loss": 0,
        "node": "WEBH",
        "speed": 308,
        "time": "2025-01-05 20:54:45"
    },
    {
        "colo": "Default",
        "ip": "2606:4700:83bd:1803:652a:c1ed:5511:68cf",
        "latency": 20,
        "line": "CU",
        "loss": 0,
        "node": "WEBH",
        "speed": 308,
        "time": "2025-01-05 20:54:44"
    },
    {
        "colo": "Default",
        "ip": "2606:4700:8d9f:f35d:a917:935:439:e52c",
        "latency": 20,
        "line": "CU",
        "loss": 0,
        "node": "WEBH",
        "speed": 308,
        "time": "2025-01-05 20:54:46"
    },
    {
        "colo": "Default",
        "ip": "2606:4700:8d9f:db46:4567:4600:a0c4:d3d3",
        "latency": 20,
        "line": "CU",
        "loss": 0,
        "node": "WEBH",
        "speed": 307,
        "time": "2025-01-05 20:54:43"
    }
]