[
    {
        "colo": "Default",
        "ip": "2606:4700:8cae:b13e:2701:5b2c:a15:5543",
        "latency": 132,
        "line": "CM",
        "loss": 0,
        "node": "CBUS",
        "speed": 622,
        "time": "2024-08-19 13:23:30"
    },
    {
        "colo": "Default",
        "ip": "2606:4700:99ea:ab05:a765:480d:a6b0:641a",
        "latency": 132,
        "line": "CM",
        "loss": 0,
        "node": "CBUS",
        "speed": 596,
        "time": "2024-08-19 13:23:31"
    },
    {
        "colo": "Default",
        "ip": "2606:4700:8cae:41ea:2770:739e:7d6:2502",
        "latency": 132,
        "line": "CM",
        "loss": 0,
        "node": "CBUS",
        "speed": 563,
        "time": "2024-08-19 13:23:31"
    },
    {
        "colo": "Default",
        "ip": "2606:4700:8cae:ff46:76cd:c02f:2861:535e",
        "latency": 132,
        "line": "CM",
        "loss": 0,
        "node": "CBUS",
        "speed": 487,
        "time": "2024-08-19 13:23:31"
    },
    {
        "colo": "Default",
        "ip": "2606:4700:99ea:9e14:375c:d016:3e9a:b192",
        "latency": 132,
        "line": "CM",
        "loss": 0,
        "node": "CBUS",
        "speed": 333,
        "time": "2024-08-19 13:23:31"
    },
    {
        "colo": "Default",
        "ip": "2606:4700:20:6e2f:5d85:dc11:3bb9:298d",
        "latency": 13,
        "line": "CT",
        "loss": 0,
        "node": "WEBH",
        "speed": 308,
        "time": "2024-08-19 13:26:18"
    },
    {
        "colo": "Default",
        "ip": "2606:4700:20:54d7:321d:a12d:8ff3:391d",
        "latency": 13,
        "line": "CT",
        "loss": 0,
        "node": "WEBH",
        "speed": 308,
        "time": "2024-08-19 13:26:17"
    },
    {
        "colo": "Default",
        "ip": "2606:4700:7:5b49:1197:af34:14f7:96af",
        "latency": 20,
        "line": "CT",
        "loss": 0,
        "node": "WEBH",
        "speed": 308,
        "time": "2024-08-19 13:26:16"
    },
    {
        "colo": "Default",
        "ip": "2606:4700:20:7968:7af9:21e2:44ff:603d",
        "latency": 13,
        "line": "CT",
        "loss": 0,
        "node": "WEBH",
        "speed": 307,
        "time": "2024-08-19 13:26:16"
    },
    {
        "colo": "Default",
        "ip": "2606:4700:7:672e:577b:dd19:6ae8:c880",
        "latency": 20,
        "line": "CT",
        "loss": 0,
        "node": "WEBH",
        "speed": 307,
        "time": "2024-08-19 13:26:15"
    },
    {
        "colo": "Default",
        "ip": "2606:4700:3011:d2b2:d64a:f8f3:c125:a400",
        "latency": 219,
        "line": "CU",
        "loss": 0,
        "node": "8465",
        "speed": 505,
        "time": "2024-08-19 12:40:44"
    },
    {
        "colo": "Default",
        "ip": "2606:4700:3011:6c6c:6a05:2cc1:afc0:99f2",
        "latency": 224,
        "line": "CU",
        "loss": 0,
        "node": "8465",
        "speed": 310,
        "time": "2024-08-19 12:40:44"
    },
    {
        "colo": "Default",
        "ip": "2606:4700:9b0a:9da9:733e:ce26:df92:44d",
        "latency": 282,
        "line": "CU",
        "loss": 0,
        "node": "8465",
        "speed": 215,
        "time": "2024-08-19 12:50:45"
    },
    {
        "colo": "Default",
        "ip": "2606:4700:9b0a:ceb6:b1f4:d7e3:297d:daee",
        "latency": 281,
        "line": "CU",
        "loss": 0,
        "node": "8465",
        "speed": 200,
        "time": "2024-08-19 12:50:45"
    },
    {
        "colo": "Default",
        "ip": "2606:4700:9b0a:a762:4e12:d322:9c25:5caf",
        "latency": 258,
        "line": "CU",
        "loss": 0,
        "node": "8465",
        "speed": 160,
        "time": "2024-08-19 12:50:45"
    }
]