[
    {
        "colo": "Default",
        "ip": "2606:4700:8d91:8eb:4171:a5fe:ccde:6950",
        "latency": 151,
        "line": "CM",
        "loss": 0,
        "node": "CBUS",
        "speed": 559,
        "time": "2024-11-30 01:09:05"
    },
    {
        "colo": "Default",
        "ip": "2606:4700:8d91:dd78:4632:3dd:8340:3ab8",
        "latency": 155,
        "line": "CM",
        "loss": 0,
        "node": "CBUS",
        "speed": 545,
        "time": "2024-11-30 01:09:06"
    },
    {
        "colo": "Default",
        "ip": "2606:4700:8d91:f360:d517:b60b:bd06:523d",
        "latency": 155,
        "line": "CM",
        "loss": 0,
        "node": "CBUS",
        "speed": 513,
        "time": "2024-11-30 01:09:05"
    },
    {
        "colo": "Default",
        "ip": "2606:4700:8d91:4bd8:3fcc:bdeb:eb90:c9db",
        "latency": 150,
        "line": "CM",
        "loss": 0,
        "node": "CBUS",
        "speed": 496,
        "time": "2024-11-30 01:09:05"
    },
    {
        "colo": "Default",
        "ip": "2606:4700:8d91:4ca5:d3da:985e:7ab6:10d2",
        "latency": 158,
        "line": "CM",
        "loss": 0,
        "node": "CBUS",
        "speed": 419,
        "time": "2024-11-30 01:09:06"
    },
    {
        "colo": "Default",
        "ip": "2606:4700:8d9e:3c5d:646e:f251:b7c5:4743",
        "latency": 20,
        "line": "CT",
        "loss": 0,
        "node": "WEBH",
        "speed": 308,
        "time": "2024-11-30 01:05:07"
    },
    {
        "colo": "Default",
        "ip": "2606:4700:8d9e:1291:45d2:7654:b11e:f4bb",
        "latency": 20,
        "line": "CT",
        "loss": 0,
        "node": "WEBH",
        "speed": 308,
        "time": "2024-11-30 01:05:06"
    },
    {
        "colo": "Default",
        "ip": "2606:4700:8d9e:347:3e1:24e4:3a0f:84f6",
        "latency": 20,
        "line": "CT",
        "loss": 0,
        "node": "WEBH",
        "speed": 308,
        "time": "2024-11-30 01:05:06"
    },
    {
        "colo": "Default",
        "ip": "2606:4700:8d9e:c5af:c499:b91f:f62:c5e6",
        "latency": 22,
        "line": "CT",
        "loss": 0,
        "node": "WEBH",
        "speed": 308,
        "time": "2024-11-30 01:05:06"
    },
    {
        "colo": "Default",
        "ip": "2606:4700:8d9e:b0d6:48c1:38be:a642:52e7",
        "latency": 20,
        "line": "CT",
        "loss": 0,
        "node": "WEBH",
        "speed": 307,
        "time": "2024-11-30 01:05:06"
    },
    {
        "colo": "Default",
        "ip": "2606:4700:8d91:8eb:4171:a5fe:ccde:6950",
        "latency": 151,
        "line": "CU",
        "loss": 0,
        "node": "CBUS",
        "speed": 559,
        "time": "2024-11-30 01:09:05"
    },
    {
        "colo": "Default",
        "ip": "2606:4700:8d91:dd78:4632:3dd:8340:3ab8",
        "latency": 155,
        "line": "CU",
        "loss": 0,
        "node": "CBUS",
        "speed": 545,
        "time": "2024-11-30 01:09:06"
    },
    {
        "colo": "Default",
        "ip": "2606:4700:8d91:f360:d517:b60b:bd06:523d",
        "latency": 155,
        "line": "CU",
        "loss": 0,
        "node": "CBUS",
        "speed": 513,
        "time": "2024-11-30 01:09:05"
    },
    {
        "colo": "Default",
        "ip": "2606:4700:8d91:4bd8:3fcc:bdeb:eb90:c9db",
        "latency": 150,
        "line": "CU",
        "loss": 0,
        "node": "CBUS",
        "speed": 496,
        "time": "2024-11-30 01:09:05"
    },
    {
        "colo": "Default",
        "ip": "2606:4700:8d91:4ca5:d3da:985e:7ab6:10d2",
        "latency": 158,
        "line": "CU",
        "loss": 0,
        "node": "CBUS",
        "speed": 419,
        "time": "2024-11-30 01:09:06"
    }
]