[
    {
        "colo": "Default",
        "ip": "2606:4700:90c4:230a:2677:609d:a5fb:80d5",
        "latency": 205,
        "line": "CM",
        "loss": 0,
        "node": "WW_HK",
        "speed": 310,
        "time": "2024-07-31 05:23:34"
    },
    {
        "colo": "Default",
        "ip": "2606:4700:90c4:14a1:ec60:ca18:a996:e1e5",
        "latency": 208,
        "line": "CM",
        "loss": 0,
        "node": "WW_HK",
        "speed": 309,
        "time": "2024-07-31 05:23:31"
    },
    {
        "colo": "Default",
        "ip": "2606:4700:8ca6:c6e7:5292:cd4f:ab76:16f2",
        "latency": 183,
        "line": "CM",
        "loss": 0,
        "node": "WW_HK",
        "speed": 308,
        "time": "2024-07-31 05:23:34"
    },
    {
        "colo": "Default",
        "ip": "2606:4700:8ca6:b0e8:ab7e:9a0a:7fe4:3e9b",
        "latency": 183,
        "line": "CM",
        "loss": 0,
        "node": "WW_HK",
        "speed": 308,
        "time": "2024-07-31 05:23:32"
    },
    {
        "colo": "Default",
        "ip": "2606:4700:8ca6:a027:147e:5522:b822:d2c0",
        "latency": 183,
        "line": "CM",
        "loss": 0,
        "node": "WW_HK",
        "speed": 307,
        "time": "2024-07-31 05:23:33"
    },
    {
        "colo": "Default",
        "ip": "2606:4700:8de8:ce44:22f2:4fa7:2ce9:d262",
        "latency": 25,
        "line": "CT",
        "loss": 0,
        "node": "WEBH",
        "speed": 310,
        "time": "2024-07-31 05:24:03"
    },
    {
        "colo": "Default",
        "ip": "2606:4700:8de8:af7e:5ee:5f08:f4b8:9dbb",
        "latency": 20,
        "line": "CT",
        "loss": 0,
        "node": "WEBH",
        "speed": 308,
        "time": "2024-07-31 05:24:04"
    },
    {
        "colo": "Default",
        "ip": "2606:4700:8de5:c422:a246:57ef:9fe6:c869",
        "latency": 25,
        "line": "CT",
        "loss": 0,
        "node": "WEBH",
        "speed": 308,
        "time": "2024-07-31 05:24:06"
    },
    {
        "colo": "Default",
        "ip": "2606:4700:8de5:5ded:269d:b3c2:d4ae:fbaf",
        "latency": 19,
        "line": "CT",
        "loss": 0,
        "node": "WEBH",
        "speed": 307,
        "time": "2024-07-31 05:24:04"
    },
    {
        "colo": "Default",
        "ip": "2606:4700:8de5:cc99:482a:5649:af6f:33fb",
        "latency": 20,
        "line": "CT",
        "loss": 0,
        "node": "WEBH",
        "speed": 307,
        "time": "2024-07-31 05:24:05"
    },
    {
        "colo": "Default",
        "ip": "2606:4700:90c4:230a:2677:609d:a5fb:80d5",
        "latency": 205,
        "line": "CU",
        "loss": 0,
        "node": "WW_HK",
        "speed": 310,
        "time": "2024-07-31 05:23:34"
    },
    {
        "colo": "Default",
        "ip": "2606:4700:90c4:14a1:ec60:ca18:a996:e1e5",
        "latency": 208,
        "line": "CU",
        "loss": 0,
        "node": "WW_HK",
        "speed": 309,
        "time": "2024-07-31 05:23:31"
    },
    {
        "colo": "Default",
        "ip": "2606:4700:8ca6:c6e7:5292:cd4f:ab76:16f2",
        "latency": 183,
        "line": "CU",
        "loss": 0,
        "node": "WW_HK",
        "speed": 308,
        "time": "2024-07-31 05:23:34"
    },
    {
        "colo": "Default",
        "ip": "2606:4700:8ca6:b0e8:ab7e:9a0a:7fe4:3e9b",
        "latency": 183,
        "line": "CU",
        "loss": 0,
        "node": "WW_HK",
        "speed": 308,
        "time": "2024-07-31 05:23:32"
    },
    {
        "colo": "Default",
        "ip": "2606:4700:8ca6:a027:147e:5522:b822:d2c0",
        "latency": 183,
        "line": "CU",
        "loss": 0,
        "node": "WW_HK",
        "speed": 307,
        "time": "2024-07-31 05:23:33"
    }
]