[
    {
        "colo": "Default",
        "ip": "2606:4700:e6:ec86:5c9:d3c3:effd:dbea",
        "latency": 2,
        "line": "CM",
        "loss": 0,
        "node": "WW_HK",
        "speed": 310,
        "time": "2024-12-11 21:36:17"
    },
    {
        "colo": "Default",
        "ip": "2606:4700:7:ca34:c44c:663d:c6ee:8bb1",
        "latency": 2,
        "line": "CM",
        "loss": 0,
        "node": "WW_HK",
        "speed": 308,
        "time": "2024-12-11 21:36:20"
    },
    {
        "colo": "Default",
        "ip": "2606:4700:7:7c09:ebfd:bca5:38ea:50e7",
        "latency": 2,
        "line": "CM",
        "loss": 0,
        "node": "WW_HK",
        "speed": 308,
        "time": "2024-12-11 21:36:20"
    },
    {
        "colo": "Default",
        "ip": "2606:4700:e6:c265:cf65:22eb:41e8:d57a",
        "latency": 2,
        "line": "CM",
        "loss": 0,
        "node": "WW_HK",
        "speed": 308,
        "time": "2024-12-11 21:36:18"
    },
    {
        "colo": "Default",
        "ip": "2606:4700:e6:1352:a0f4:a5c6:5efc:f65b",
        "latency": 2,
        "line": "CM",
        "loss": 0,
        "node": "WW_HK",
        "speed": 307,
        "time": "2024-12-11 21:36:19"
    },
    {
        "colo": "Default",
        "ip": "2606:4700:85d1:bd2d:e6c1:5aa:c038:9df4",
        "latency": 20,
        "line": "CT",
        "loss": 0,
        "node": "WEBH",
        "speed": 309,
        "time": "2024-12-13 11:14:59"
    },
    {
        "colo": "Default",
        "ip": "2606:4700:85d1:55d0:ae00:d52f:2066:c369",
        "latency": 19,
        "line": "CT",
        "loss": 0,
        "node": "WEBH",
        "speed": 309,
        "time": "2024-12-13 11:15:00"
    },
    {
        "colo": "Default",
        "ip": "2606:4700:85d1:e781:6087:de33:9dc0:5634",
        "latency": 20,
        "line": "CT",
        "loss": 0,
        "node": "WEBH",
        "speed": 308,
        "time": "2024-12-13 11:15:02"
    },
    {
        "colo": "Default",
        "ip": "2606:4700:85d1:3967:de27:a08c:4777:6d0e",
        "latency": 22,
        "line": "CT",
        "loss": 0,
        "node": "WEBH",
        "speed": 307,
        "time": "2024-12-13 11:14:59"
    },
    {
        "colo": "Default",
        "ip": "2606:4700:85d1:b8cb:968d:4aee:171e:33b3",
        "latency": 24,
        "line": "CT",
        "loss": 0,
        "node": "WEBH",
        "speed": 307,
        "time": "2024-12-13 11:15:01"
    },
    {
        "colo": "Default",
        "ip": "2606:4700:e6:ec86:5c9:d3c3:effd:dbea",
        "latency": 2,
        "line": "CU",
        "loss": 0,
        "node": "WW_HK",
        "speed": 310,
        "time": "2024-12-11 21:36:17"
    },
    {
        "colo": "Default",
        "ip": "2606:4700:7:ca34:c44c:663d:c6ee:8bb1",
        "latency": 2,
        "line": "CU",
        "loss": 0,
        "node": "WW_HK",
        "speed": 308,
        "time": "2024-12-11 21:36:20"
    },
    {
        "colo": "Default",
        "ip": "2606:4700:7:7c09:ebfd:bca5:38ea:50e7",
        "latency": 2,
        "line": "CU",
        "loss": 0,
        "node": "WW_HK",
        "speed": 308,
        "time": "2024-12-11 21:36:20"
    },
    {
        "colo": "Default",
        "ip": "2606:4700:e6:c265:cf65:22eb:41e8:d57a",
        "latency": 2,
        "line": "CU",
        "loss": 0,
        "node": "WW_HK",
        "speed": 308,
        "time": "2024-12-11 21:36:18"
    },
    {
        "colo": "Default",
        "ip": "2606:4700:e6:1352:a0f4:a5c6:5efc:f65b",
        "latency": 2,
        "line": "CU",
        "loss": 0,
        "node": "WW_HK",
        "speed": 307,
        "time": "2024-12-11 21:36:19"
    }
]