[
    {
        "colo": "Default",
        "ip": "2606:4700:90d2:5ddd:25ab:9b5b:e019:415f",
        "latency": 138,
        "line": "CM",
        "loss": 0,
        "node": "CBUS",
        "speed": 468,
        "time": "2024-05-28 14:40:44"
    },
    {
        "colo": "Default",
        "ip": "2606:4700:90d2:74fa:4c6a:5645:8918:af35",
        "latency": 137,
        "line": "CM",
        "loss": 0,
        "node": "CBUS",
        "speed": 456,
        "time": "2024-05-28 14:40:44"
    },
    {
        "colo": "Default",
        "ip": "2606:4700:90d2:11de:e330:c699:175d:877c",
        "latency": 138,
        "line": "CM",
        "loss": 0,
        "node": "CBUS",
        "speed": 455,
        "time": "2024-05-28 14:40:44"
    },
    {
        "colo": "Default",
        "ip": "2606:4700:90d2:aad3:3444:39b4:3050:1245",
        "latency": 138,
        "line": "CM",
        "loss": 0,
        "node": "CBUS",
        "speed": 424,
        "time": "2024-05-28 14:40:44"
    },
    {
        "colo": "Default",
        "ip": "2606:4700:90d2:2696:be2f:2715:142f:1c12",
        "latency": 138,
        "line": "CM",
        "loss": 0,
        "node": "CBUS",
        "speed": 339,
        "time": "2024-05-28 14:40:44"
    },
    {
        "colo": "Default",
        "ip": "2606:4700:90d2:5ddd:25ab:9b5b:e019:415f",
        "latency": 138,
        "line": "CT",
        "loss": 0,
        "node": "CBUS",
        "speed": 468,
        "time": "2024-05-28 14:40:44"
    },
    {
        "colo": "Default",
        "ip": "2606:4700:90d2:74fa:4c6a:5645:8918:af35",
        "latency": 137,
        "line": "CT",
        "loss": 0,
        "node": "CBUS",
        "speed": 456,
        "time": "2024-05-28 14:40:44"
    },
    {
        "colo": "Default",
        "ip": "2606:4700:90d2:11de:e330:c699:175d:877c",
        "latency": 138,
        "line": "CT",
        "loss": 0,
        "node": "CBUS",
        "speed": 455,
        "time": "2024-05-28 14:40:44"
    },
    {
        "colo": "Default",
        "ip": "2606:4700:90d2:aad3:3444:39b4:3050:1245",
        "latency": 138,
        "line": "CT",
        "loss": 0,
        "node": "CBUS",
        "speed": 424,
        "time": "2024-05-28 14:40:44"
    },
    {
        "colo": "Default",
        "ip": "2606:4700:90d2:2696:be2f:2715:142f:1c12",
        "latency": 138,
        "line": "CT",
        "loss": 0,
        "node": "CBUS",
        "speed": 339,
        "time": "2024-05-28 14:40:44"
    },
    {
        "colo": "Default",
        "ip": "2606:4700:90d2:5ddd:25ab:9b5b:e019:415f",
        "latency": 138,
        "line": "CU",
        "loss": 0,
        "node": "CBUS",
        "speed": 468,
        "time": "2024-05-28 14:40:44"
    },
    {
        "colo": "Default",
        "ip": "2606:4700:90d2:74fa:4c6a:5645:8918:af35",
        "latency": 137,
        "line": "CU",
        "loss": 0,
        "node": "CBUS",
        "speed": 456,
        "time": "2024-05-28 14:40:44"
    },
    {
        "colo": "Default",
        "ip": "2606:4700:90d2:11de:e330:c699:175d:877c",
        "latency": 138,
        "line": "CU",
        "loss": 0,
        "node": "CBUS",
        "speed": 455,
        "time": "2024-05-28 14:40:44"
    },
    {
        "colo": "Default",
        "ip": "2606:4700:90d2:aad3:3444:39b4:3050:1245",
        "latency": 138,
        "line": "CU",
        "loss": 0,
        "node": "CBUS",
        "speed": 424,
        "time": "2024-05-28 14:40:44"
    },
    {
        "colo": "Default",
        "ip": "2606:4700:90d2:2696:be2f:2715:142f:1c12",
        "latency": 138,
        "line": "CU",
        "loss": 0,
        "node": "CBUS",
        "speed": 339,
        "time": "2024-05-28 14:40:44"
    }
]