[
    {
        "colo": "Default",
        "ip": "2606:4700:8ca7:83ed:e2a1:1ffb:83fe:a3d1",
        "latency": 137,
        "line": "CM",
        "loss": 0,
        "node": "CBUS",
        "speed": 530,
        "time": "2024-08-23 05:24:03"
    },
    {
        "colo": "Default",
        "ip": "2606:4700:8ca7:8cf0:372d:35b6:767a:fb95",
        "latency": 137,
        "line": "CM",
        "loss": 0,
        "node": "CBUS",
        "speed": 499,
        "time": "2024-08-23 05:24:03"
    },
    {
        "colo": "Default",
        "ip": "2606:4700:8ca7:d408:41a9:6b9:d7b4:b1e7",
        "latency": 137,
        "line": "CM",
        "loss": 0,
        "node": "CBUS",
        "speed": 487,
        "time": "2024-08-23 05:24:03"
    },
    {
        "colo": "Default",
        "ip": "2606:4700:8ca7:20cf:d999:a329:f08b:e07",
        "latency": 136,
        "line": "CM",
        "loss": 0,
        "node": "CBUS",
        "speed": 483,
        "time": "2024-08-23 05:24:03"
    },
    {
        "colo": "Default",
        "ip": "2606:4700:8ca7:d92a:58fd:f117:8ae0:885a",
        "latency": 137,
        "line": "CM",
        "loss": 0,
        "node": "CBUS",
        "speed": 476,
        "time": "2024-08-23 05:24:03"
    },
    {
        "colo": "Default",
        "ip": "2606:4700:9a68:8253:b23c:1b83:df55:2d09",
        "latency": 24,
        "line": "CT",
        "loss": 0,
        "node": "WEBH",
        "speed": 310,
        "time": "2024-08-23 05:16:29"
    },
    {
        "colo": "Default",
        "ip": "2606:4700:19:edde:93b0:472d:daea:2ed1",
        "latency": 1,
        "line": "CT",
        "loss": 0,
        "node": "WEBH",
        "speed": 309,
        "time": "2024-08-23 05:16:36"
    },
    {
        "colo": "Default",
        "ip": "2606:4700:9a68:aa70:3403:f86a:af44:b19e",
        "latency": 20,
        "line": "CT",
        "loss": 0,
        "node": "WEBH",
        "speed": 308,
        "time": "2024-08-23 05:16:34"
    },
    {
        "colo": "Default",
        "ip": "2606:4700:19:3918:6797:68dc:5b7a:c593",
        "latency": 1,
        "line": "CT",
        "loss": 0,
        "node": "WEBH",
        "speed": 308,
        "time": "2024-08-23 05:16:36"
    },
    {
        "colo": "Default",
        "ip": "2606:4700:19:73f8:75b3:aad5:75c9:68af",
        "latency": 1,
        "line": "CT",
        "loss": 0,
        "node": "WEBH",
        "speed": 307,
        "time": "2024-08-23 05:16:29"
    },
    {
        "colo": "Default",
        "ip": "2606:4700:300b:64b1:6fd3:89b:b9e6:d9c",
        "latency": 201,
        "line": "CU",
        "loss": 0,
        "node": "8465",
        "speed": 310,
        "time": "2024-08-23 05:10:32"
    },
    {
        "colo": "Default",
        "ip": "2606:4700:300b:483f:cbaf:6ae8:33aa:3168",
        "latency": 183,
        "line": "CU",
        "loss": 0,
        "node": "8465",
        "speed": 310,
        "time": "2024-08-23 05:10:32"
    },
    {
        "colo": "Default",
        "ip": "2606:4700:8d9f:39c2:647:dcc:996d:8ac6",
        "latency": 218,
        "line": "CU",
        "loss": 0,
        "node": "8465",
        "speed": 290,
        "time": "2024-08-23 05:00:30"
    },
    {
        "colo": "Default",
        "ip": "2606:4700:300b:c263:c897:60dc:b7ee:9377",
        "latency": 203,
        "line": "CU",
        "loss": 0,
        "node": "8465",
        "speed": 215,
        "time": "2024-08-23 05:10:32"
    },
    {
        "colo": "Default",
        "ip": "2606:4700:8d9f:853c:735a:d1f8:9a67:f859",
        "latency": 210,
        "line": "CU",
        "loss": 0,
        "node": "8465",
        "speed": 215,
        "time": "2024-08-23 05:00:30"
    }
]